[
    {
        "uid": "4",
        "name": "miyazaki"
    },
    {
        "uid": "5",
        "name": "zushi"
    },
    {
        "uid": "8",
        "name": "miyazaki0"
    },
    {
        "uid": "6",
        "name": "banno0"
    },
    {
        "uid": "7",
        "name": "banno1"
    },
    {
        "uid": "70610078",
        "name": "banno"
    },
    {
        "uid": "9",
        "name": "miyazaki1"
    },
    {
        "uid": "10",
        "name": "zushi1"
    },
    {
        "uid": "11",
        "name": "zushi2"
    },
    {
        "uid": "12",
        "name": "guest1"
    },
    {
        "uid": "13",
        "name": "guest2"
    },
    {
        "uid": "14",
        "name": "guest3"
    },
    {
        "uid": "15",
        "name": "guest4"
    },
    {
        "uid": "16",
        "name": "guest5"
    },
    {
        "uid": "17",
        "name": "zushi3"
    },
    {
        "uid": "18",
        "name": "miyazaki2"
    },
    {
        "uid": "30914025",
        "name": "30914025"
    },
    {
        "uid": "30914026",
        "name": "30914026"
    },
    {
        "uid": "30914904",
        "name": "30914904"
    },
    {
        "uid": "30814907",
        "name": "30814907"
    },
    {
        "uid": "60910014",
        "name": "60910014"
    },
    {
        "uid": "60910020",
        "name": "60910020"
    },
    {
        "uid": "60910022",
        "name": "60910022"
    },
    {
        "uid": "60910037",
        "name": "60910037"
    },
    {
        "uid": "60910044",
        "name": "60910044"
    },
    {
        "uid": "60910046",
        "name": "60910046"
    },
    {
        "uid": "60910074",
        "name": "60910074"
    },
    {
        "uid": "60910090",
        "name": "60910090"
    },
    {
        "uid": "60910103",
        "name": "60910103"
    },
    {
        "uid": "60911041",
        "name": "60911041"
    },
    {
        "uid": "60911043",
        "name": "60911043"
    },
    {
        "uid": "60911060",
        "name": "60911060"
    },
    {
        "uid": "60911065",
        "name": "60911065"
    },
    {
        "uid": "60911069",
        "name": "60911069"
    },
    {
        "uid": "60911072",
        "name": "60911072"
    },
    {
        "uid": "90910001",
        "name": "90910001"
    },
    {
        "uid": "90910034",
        "name": "90910034"
    },
    {
        "uid": "90910038",
        "name": "90910038"
    },
    {
        "uid": "90910033",
        "name": "90910033"
    },
    {
        "uid": "90910004",
        "name": "90910004"
    },
    {
        "uid": "19",
        "name": "zushi4"
    },
    {
        "uid": "20",
        "name": "banno2"
    },
    {
        "uid": "201912060",
        "name": "201912060"
    },
    {
        "uid": "201912090",
        "name": "201912090"
    },
    {
        "uid": "201912100",
        "name": "201912100"
    },
    {
        "uid": "201912120",
        "name": "201912120"
    },
    {
        "uid": "201912130",
        "name": "201912130"
    },
    {
        "uid": "20191214",
        "name": "20191214"
    },
    {
        "uid": "9000",
        "name": "9000"
    },
    {
        "uid": "202007010",
        "name": "202007010"
    },
    {
        "uid": "202007011",
        "name": "202007011"
    },
    {
        "uid": "202007012",
        "name": "202007012"
    },
    {
        "uid": "202007013",
        "name": "202007013"
    },
    {
        "uid": "202007014",
        "name": "202007014"
    },
    {
        "uid": "902",
        "name": "0902"
    },
    {
        "uid": "9131114",
        "name": "yamakawa"
    },
    {
        "uid": "99998888",
        "name": "temp"
    }
]